{
   "$type":"GDO.Apps.Maps.Core.Map, GDO.Apps.Maps",
   "CurrentView":0,
   "Views":{
      "$type":"GDO.Apps.Maps.Core.View[], GDO.Apps.Maps",
      "$values":[
         {
            "$type":"GDO.Apps.Maps.Core.View, GDO.Apps.Maps",
            "Id":0,
            "Name":"Default",
            "ClassName":null,
            "Type":null,
            "Editables":{
               "$type":"System.Collections.Generic.List`1[[System.String, mscorlib]], mscorlib",
               "$values":[

               ]
            },
            "Position":{
               "$type":"GDO.Apps.Maps.Core.Position, GDO.Apps.Maps",
               "TopLeft":{
                  "$type":"System.Double[], mscorlib",
                  "$values":[
                     0.0,
                     0.0,
                     0.0,
                     0.0
                  ]
               },
               "Center":{
                  "$type":"System.Double[], mscorlib",
                  "$values":[
                     0.0,
                     0.0,
                     0.0,
                     0.0
                  ]
               },
               "BottomRight":{
                  "$type":"System.Double[], mscorlib",
                  "$values":[
                     0.0,
                     0.0,
                     0.0,
                     0.0
                  ]
               },
               "Resolution":0.0,
               "Zoom":0
            },
            "Rotation":0.0,
            "Width":100,
            "Height":100,
            "Projection":"EPSG:4326"
         }
      ]
   },
   "Formats":{
      "$type":"GDO.Apps.Maps.Core.Format[], GDO.Apps.Maps",
      "$values":[
      ]
   },
   "Styles":{
      "$type":"GDO.Apps.Maps.Core.Style[], GDO.Apps.Maps",
      "$values":[

      ]
   },
   "Sources":{
      "$type":"GDO.Apps.Maps.Core.Source[], GDO.Apps.Maps",
      "$values":[

      ]
   },
   "Layers":{
      "$type":"GDO.Apps.Maps.Core.Layer[], GDO.Apps.Maps",
      "$values":[

      ]
   }
}